setup.cfg
setup.py
wsgihatenaauth/__init__.py
wsgihatenaauth.egg-info/PKG-INFO
wsgihatenaauth.egg-info/SOURCES.txt
wsgihatenaauth.egg-info/dependency_links.txt
wsgihatenaauth.egg-info/entry_points.txt
wsgihatenaauth.egg-info/not-zip-safe
wsgihatenaauth.egg-info/requires.txt
wsgihatenaauth.egg-info/top_level.txt
