Metadata-Version: 1.0
Name: wsgihatenaauth
Version: 0.1dev
Summary: wsgi middlewar
Home-page: UNKNOWN
Author: Atsushi Odagiri
Author-email: aodagx@gmail.com
License: BSD
Keywords: wsgi middleware
Platform: UNKNOWN
